{
  "scraped_at": 1784576423.624339,
  "rows": [
    {
      "date": "Mar 3",
      "opponent": "vs. Chatham",
      "score": "L, 10-1",
      "gp": 1.0,
      "ab": 0.0,
      "h": 0.0,
      "rbi": 0.0,
      "bb": null,
      "2b": null,
      "3b": null,
      "hr": null,
      "xbh": 0.0,
      "k": null,
      "avg": null,
      "obp": null,
      "slg": null,
      "hbp": null,
      "sf": null,
      "sh": null,
      "hdp": null,
      "go": null,
      "fo": null,
      "go/fo": null,
      "pa": 0.0
    },
    {
      "date": "Mar 4",
      "opponent": "vs. John Carroll",
      "score": "L, 19-2",
      "gp": 1.0,
      "ab": 1.0,
      "h": 0.0,
      "rbi": 0.0,
      "bb": null,
      "2b": null,
      "3b": null,
      "hr": null,
      "xbh": 0.0,
      "k": 1.0,
      "avg": 0.0,
      "obp": 0.0,
      "slg": 0.0,
      "hbp": null,
      "sf": null,
      "sh": null,
      "hdp": null,
      "go": null,
      "fo": null,
      "go/fo": null,
      "pa": 1.0
    },
    {
      "date": "Mar 7",
      "opponent": "vs. Thomas (ME)",
      "score": "W, 12-2",
      "gp": 1.0,
      "ab": 0.0,
      "h": 0.0,
      "rbi": 0.0,
      "bb": null,
      "2b": null,
      "3b": null,
      "hr": null,
      "xbh": 0.0,
      "k": null,
      "avg": null,
      "obp": null,
      "slg": null,
      "hbp": null,
      "sf": null,
      "sh": null,
      "hdp": null,
      "go": null,
      "fo": null,
      "go/fo": null,
      "pa": 0.0
    },
    {
      "date": "Mar 21",
      "opponent": "Gordon",
      "score": "W, 4-0",
      "gp": 1.0,
      "ab": 0.0,
      "h": 0.0,
      "rbi": 0.0,
      "bb": null,
      "2b": null,
      "3b": null,
      "hr": null,
      "xbh": 0.0,
      "k": null,
      "avg": null,
      "obp": null,
      "slg": null,
      "hbp": null,
      "sf": null,
      "sh": null,
      "hdp": null,
      "go": null,
      "fo": null,
      "go/fo": null,
      "pa": 0.0
    },
    {
      "date": "Mar 21",
      "opponent": "Gordon",
      "score": "L, 5-1",
      "gp": 1.0,
      "ab": 2.0,
      "h": 0.0,
      "rbi": 0.0,
      "bb": null,
      "2b": null,
      "3b": null,
      "hr": null,
      "xbh": 0.0,
      "k": 2.0,
      "avg": 0.0,
      "obp": 0.0,
      "slg": 0.0,
      "hbp": null,
      "sf": null,
      "sh": null,
      "hdp": null,
      "go": null,
      "fo": null,
      "go/fo": null,
      "pa": 2.0
    },
    {
      "date": "Mar 24",
      "opponent": "at MCLA",
      "score": "W, 10-0",
      "gp": 1.0,
      "ab": 2.0,
      "h": 2.0,
      "rbi": 0.0,
      "bb": null,
      "2b": null,
      "3b": null,
      "hr": null,
      "xbh": 0.0,
      "k": null,
      "avg": 1.0,
      "obp": 1.0,
      "slg": 1.0,
      "hbp": null,
      "sf": null,
      "sh": null,
      "hdp": null,
      "go": null,
      "fo": null,
      "go/fo": null,
      "pa": 2.0
    },
    {
      "date": "Apr 10",
      "opponent": "at Westfield St.",
      "score": "L, 10-6",
      "gp": 1.0,
      "ab": 0.0,
      "h": 0.0,
      "rbi": 0.0,
      "bb": null,
      "2b": null,
      "3b": null,
      "hr": null,
      "xbh": 0.0,
      "k": null,
      "avg": null,
      "obp": null,
      "slg": null,
      "hbp": null,
      "sf": null,
      "sh": null,
      "hdp": null,
      "go": null,
      "fo": null,
      "go/fo": null,
      "pa": 0.0
    },
    {
      "date": "Apr 18",
      "opponent": "at Salem St.",
      "score": "L, 3-0",
      "gp": 1.0,
      "ab": 0.0,
      "h": 0.0,
      "rbi": 0.0,
      "bb": null,
      "2b": null,
      "3b": null,
      "hr": null,
      "xbh": 0.0,
      "k": null,
      "avg": null,
      "obp": null,
      "slg": null,
      "hbp": null,
      "sf": null,
      "sh": null,
      "hdp": null,
      "go": null,
      "fo": null,
      "go/fo": null,
      "pa": 0.0
    },
    {
      "date": "May 2",
      "opponent": "at Bridgewater St.",
      "score": "L, 13-1",
      "gp": 1.0,
      "ab": 1.0,
      "h": 0.0,
      "rbi": 0.0,
      "bb": null,
      "2b": null,
      "3b": null,
      "hr": null,
      "xbh": 0.0,
      "k": null,
      "avg": 0.0,
      "obp": 0.0,
      "slg": 0.0,
      "hbp": null,
      "sf": null,
      "sh": null,
      "hdp": null,
      "go": 1.0,
      "fo": null,
      "go/fo": null,
      "pa": 1.0
    }
  ]
}